castoredc_api/__init__.py
castoredc_api/auth/__init__.py
castoredc_api/auth/auth_data.py
castoredc_api/client/__init__.py
castoredc_api/client/castoredc_api_client.py
castoredc_api/client/client_options.py
castoredc_api/importer/__init__.py
castoredc_api/importer/async_helpers.py
castoredc_api/importer/async_import.py
castoredc_api/importer/helpers.py
castoredc_api/importer/import_data.py
castoredc_api/importer/sync_import.py
castoredc_api/study/__init__.py
castoredc_api/study/castor_study.py
castoredc_api/study/castor_objects/__init__.py
castoredc_api/study/castor_objects/castor_data_point.py
castoredc_api/study/castor_objects/castor_field.py
castoredc_api/study/castor_objects/castor_form.py
castoredc_api/study/castor_objects/castor_form_instance.py
castoredc_api/study/castor_objects/castor_record.py
castoredc_api/study/castor_objects/castor_report_form_instance.py
castoredc_api/study/castor_objects/castor_step.py
castoredc_api/study/castor_objects/castor_study_form_instance.py
castoredc_api/study/castor_objects/castor_survey_form_instance.py
castoredc_api/tests/__init__.py
castoredc_api/tests/conftest.py
castoredc_api/tests/test_client.py
castoredc_api/tests/test_api_endpoints/__init__.py
castoredc_api/tests/test_api_endpoints/data_models.py
castoredc_api/tests/test_api_endpoints/fixtures_api.py
castoredc_api/tests/test_api_endpoints/helpers_api_endpoints.py
castoredc_api/tests/test_api_endpoints/test_audit_trail_endpoints.py
castoredc_api/tests/test_api_endpoints/test_country_endpoints.py
castoredc_api/tests/test_api_endpoints/test_data_point_collection_endpoints.py
castoredc_api/tests/test_api_endpoints/test_device_token_endpoints.py
castoredc_api/tests/test_api_endpoints/test_econsent_endpoints.py
castoredc_api/tests/test_api_endpoints/test_export_endpoints.py
castoredc_api/tests/test_api_endpoints/test_field_dependency_endpoints.py
castoredc_api/tests/test_api_endpoints/test_field_endpoints.py
castoredc_api-0.1.9.1.dist-info/LICENSE.md
castoredc_api-0.1.9.1.dist-info/METADATA
castoredc_api-0.1.9.1.dist-info/WHEEL
castoredc_api-0.1.9.1.dist-info/top_level.txt
castoredc_api-0.1.9.1.dist-info/RECORD
