Metadata-Version: 2.1
Name: castoredc-api
Version: 0.1.9.1
Summary: Python wrapper for the Castor EDC API
Home-page: https://github.com/reiniervlinschoten/castoredc_api
Author: Reinier van Linschoten
Author-email: mail@reiniervl.com
Maintainer: Reinier van Linschoten
Maintainer-email: mail@reiniervl.com
License: MIT
License-File: LICENSE.md
Requires-Dist: pandas (>=1.4.3)
Requires-Dist: numpy (>=1.23.2)
Requires-Dist: openpyxl (>=3.0.9)
Requires-Dist: tqdm (>=4.64.0)
Requires-Dist: httpx (>=0.23.0)
Requires-Dist: ratelimiter (>=1.2.0)
Requires-Dist: importlib-metadata (>=1.0) ; python_version < "3.8"
